odoo10_addon_hr_family-10.0.1.1.0-nspkg.pth
odoo/addons/hr_family/README.rst
odoo/addons/hr_family/__init__.py
odoo/addons/hr_family/__manifest__.py
odoo/addons/hr_family/i18n/ar.po
odoo/addons/hr_family/i18n/cs_CZ.po
odoo/addons/hr_family/i18n/de.po
odoo/addons/hr_family/i18n/es.po
odoo/addons/hr_family/i18n/fi.po
odoo/addons/hr_family/i18n/fr.po
odoo/addons/hr_family/i18n/hr.po
odoo/addons/hr_family/i18n/hr_HR.po
odoo/addons/hr_family/i18n/hr_family.pot
odoo/addons/hr_family/i18n/it.po
odoo/addons/hr_family/i18n/lt.po
odoo/addons/hr_family/i18n/nl_NL.po
odoo/addons/hr_family/i18n/pl.po
odoo/addons/hr_family/i18n/pt_BR.po
odoo/addons/hr_family/i18n/ro.po
odoo/addons/hr_family/i18n/sl.po
odoo/addons/hr_family/models/__init__.py
odoo/addons/hr_family/models/hr_children.py
odoo/addons/hr_family/models/hr_employee.py
odoo/addons/hr_family/security/ir.model.access.csv
odoo/addons/hr_family/static/description/icon.png
odoo/addons/hr_family/views/hr_children.xml
odoo/addons/hr_family/views/hr_employee.xml
odoo10_addon_hr_family-10.0.1.1.0.dist-info/METADATA
odoo10_addon_hr_family-10.0.1.1.0.dist-info/WHEEL
odoo10_addon_hr_family-10.0.1.1.0.dist-info/namespace_packages.txt
odoo10_addon_hr_family-10.0.1.1.0.dist-info/top_level.txt
odoo10_addon_hr_family-10.0.1.1.0.dist-info/RECORD
